{
  "parent": "ratlantis:token",
  "criteria": {
    "visit_ratlantis": {
      "conditions": {
        "to": "rats:ratlantis"
      },
      "trigger": "minecraft:changed_dimension"
    }
  },
  "display": {
    "announce_to_chat": false,
    "description": {
      "translate": "advancement.ratlantis.ratlantis.desc"
    },
    "frame": "goal",
    "hidden": false,
    "icon": {
      "item": "rats:ratlantis_portal"
    },
    "show_toast": true,
    "title": {
      "translate": "advancement.ratlantis.ratlantis.title"
    }
  },
  "requirements": [
    [
      "visit_ratlantis"
    ]
  ],
  "sends_telemetry_event": true
}