{
  "type": "minecraft:entity",
  "pools": [
    {
      "bonus_rolls": 0.0,
      "entries": [
        {
          "type": "minecraft:item",
          "functions": [
            {
              "add": false,
              "count": {
                "type": "minecraft:uniform",
                "max": 1.0,
                "min": 0.0
              },
              "function": "minecraft:set_count"
            }
          ],
          "name": "rats:cooked_rat"
        }
      ],
      "rolls": 1.0
    },
    {
      "bonus_rolls": 0.0,
      "entries": [
        {
          "type": "minecraft:item",
          "conditions": [
            {
              "chance": 0.05,
              "condition": "minecraft:random_chance_with_looting",
              "looting_multiplier": 0.05
            }
          ],
          "name": "rats:rat_skull"
        }
      ],
      "rolls": 1.0
    },
    {
      "bonus_rolls": 0.0,
      "conditions": [
        {
          "chance": 0.5,
          "condition": "minecraft:random_chance_with_looting",
          "looting_multiplier": 0.1
        }
      ],
      "entries": [
        {
          "type": "minecraft:item",
          "name": "rats:nether_cheese"
        },
        {
          "type": "minecraft:item",
          "name": "minecraft:magma_cream"
        }
      ],
      "functions": [
        {
          "count": {
            "type": "minecraft:uniform",
            "max": 1.0,
            "min": 0.0
          },
          "function": "minecraft:looting_enchant"
        }
      ],
      "rolls": 1.0
    },
    {
      "bonus_rolls": 0.0,
      "conditions": [
        {
          "chance": 0.1,
          "condition": "minecraft:random_chance_with_looting",
          "looting_multiplier": 0.02
        }
      ],
      "entries": [
        {
          "type": "minecraft:item",
          "name": "rats:rat_paw"
        }
      ],
      "rolls": 1.0
    }
  ]
}