{
    "display": {
        "icon": {
            "item": "rats:rat_water_bottle"
        },
        "title": {
            "translate": "advancements.rats.rat_cage_decoration.title"
        },
        "description": {
            "translate": "advancements.rats.rat_cage_decoration.description"
        }
    },
    "parent": "rats:rats/rat_cage",
    "criteria": {
        "1": {
            "trigger": "minecraft:inventory_changed",
            "conditions": {
                "items": [
                    {
                        "tag": "rats:rat_cage_decorations"
                    }
                ]
            }
        }
    }
}