{
  "parent": "minecraft:recipes/root",
  "criteria": {
    "has_arrow": {
      "conditions": {
        "items": [
          {
            "tag": "minecraft:arrows"
          }
        ]
      },
      "trigger": "minecraft:inventory_changed"
    },
    "has_bow": {
      "conditions": {
        "items": [
          {
            "items": [
              "minecraft:bow"
            ]
          }
        ]
      },
      "trigger": "minecraft:inventory_changed"
    },
    "has_the_recipe": {
      "conditions": {
        "recipe": "rats:upgrades/bow_upgrade"
      },
      "trigger": "minecraft:recipe_unlocked"
    },
    "has_upgrade": {
      "conditions": {
        "items": [
          {
            "items": [
              "rats:rat_upgrade_basic"
            ]
          }
        ]
      },
      "trigger": "minecraft:inventory_changed"
    }
  },
  "requirements": [
    [
      "has_bow",
      "has_upgrade",
      "has_arrow",
      "has_the_recipe"
    ]
  ],
  "rewards": {
    "recipes": [
      "rats:upgrades/bow_upgrade"
    ]
  },
  "sends_telemetry_event": false
}