{
  "type": "minecraft:crafting_shaped",
  "category": "misc",
  "key": {
    "A": {
      "item": "rats:rat_upgrade_armor"
    },
    "B": {
      "tag": "forge:storage_blocks/diamond"
    },
    "D": {
      "tag": "forge:gems/diamond"
    },
    "F": {
      "item": "rats:rat_upgrade_strength"
    },
    "H": {
      "item": "rats:rat_upgrade_health"
    },
    "S": {
      "item": "minecraft:diamond_sword"
    }
  },
  "pattern": [
    "DSD",
    "HFA",
    "DBD"
  ],
  "result": {
    "item": "rats:rat_upgrade_warrior"
  },
  "show_notification": true
}